MANIFEST.in
README.md
changelog.md
setup.cfg
setup.py
ConfigSpaceNNI/__init__.py
ConfigSpaceNNI/__version__.py
ConfigSpaceNNI/c_util.pyx
ConfigSpaceNNI/conditions.pxd
ConfigSpaceNNI/conditions.pyx
ConfigSpaceNNI/configuration_space.py
ConfigSpaceNNI/convert.py
ConfigSpaceNNI/exceptions.py
ConfigSpaceNNI/forbidden.pxd
ConfigSpaceNNI/forbidden.pyx
ConfigSpaceNNI/hyperparameters.pxd
ConfigSpaceNNI/hyperparameters.pyx
ConfigSpaceNNI/util.py
ConfigSpaceNNI.egg-info/PKG-INFO
ConfigSpaceNNI.egg-info/SOURCES.txt
ConfigSpaceNNI.egg-info/dependency_links.txt
ConfigSpaceNNI.egg-info/requires.txt
ConfigSpaceNNI.egg-info/top_level.txt
ConfigSpaceNNI/nx/__init__.py
ConfigSpaceNNI/nx/exception.py
ConfigSpaceNNI/nx/release.py
ConfigSpaceNNI/nx/algorithms/__init__.py
ConfigSpaceNNI/nx/algorithms/cycles.py
ConfigSpaceNNI/nx/algorithms/dag.py
ConfigSpaceNNI/nx/algorithms/components/__init__.py
ConfigSpaceNNI/nx/algorithms/components/strongly_connected.py
ConfigSpaceNNI/nx/classes/__init__.py
ConfigSpaceNNI/nx/classes/digraph.py
ConfigSpaceNNI/nx/classes/graph.py
ConfigSpaceNNI/read_and_write/__init__.py
ConfigSpaceNNI/read_and_write/irace.py
ConfigSpaceNNI/read_and_write/json.py
ConfigSpaceNNI/read_and_write/pbs.py
ConfigSpaceNNI/read_and_write/pcs.py
ConfigSpaceNNI/read_and_write/pcs_new.py
ConfigSpaceNNI/read_and_write/pyll.py
ConfigSpaceNNI/read_and_write/spearmint_april2013_mod_spearmint_pb2.py
test/__init__.py
test/test_conditions.py
test/test_configuration_space.py
test/test_forbidden.py
test/test_hyperparameters.py
test/test_util.py
test/read_and_write/__init__.py
test/read_and_write/test_irace_writer.py
test/read_and_write/test_json.py
test/read_and_write/test_pb_converter.py
test/read_and_write/test_pcs_converter.py
test/read_and_write/test_pyll_util.py
test/test_converters_and_test_searchspaces/__init__.py
test/test_converters_and_test_searchspaces/test_sample_configuration_spaces.py
test/test_searchspaces/__init__.py